gl-query/__init__.py
gl-query/__main__.py
gl-query/query.py
gl_query/__init__.py
gl_query/query.py
gl_query-0.0.0.dist-info/LICENSE.txt
gl_query-0.0.0.dist-info/METADATA
gl_query-0.0.0.dist-info/WHEEL
gl_query-0.0.0.dist-info/entry_points.txt
gl_query-0.0.0.dist-info/top_level.txt
gl_query-0.0.0.dist-info/RECORD
