Metadata-Version: 2.1
Name: gl-query
Version: 0.0.0
Summary: Query GitLab API for useful project and pipeline information.
Home-page: https://github.com/jay-jain/gl-query
Author: Jay Jain
License: MIT
Platform: UNKNOWN
Classifier: License :: OSI Approved :: MIT License
Classifier: Programming Language :: Python :: 3
Classifier: Programming Language :: Python :: 3.7
License-File: LICENSE.txt
Requires-Dist: requests
Requires-Dist: prettytable
